semcluster/__init__.py
semcluster/esa.py
semcluster/semcluster.py
semcluster/util.py
semcluster/matrix/0.mtx
semcluster/matrix/1.mtx
semcluster/matrix/10.mtx
semcluster/matrix/100.mtx
semcluster/matrix/101.mtx
semcluster/matrix/102.mtx
semcluster/matrix/103.mtx
semcluster/matrix/104.mtx
semcluster/matrix/105.mtx
semcluster/matrix/106.mtx
semcluster/matrix/107.mtx
semcluster/matrix/108.mtx
semcluster/matrix/109.mtx
semcluster/matrix/11.mtx
semcluster/matrix/110.mtx
semcluster/matrix/111.mtx
semcluster/matrix/112.mtx
semcluster/matrix/12.mtx
semcluster/matrix/13.mtx
semcluster/matrix/14.mtx
semcluster/matrix/15.mtx
semcluster/matrix/16.mtx
semcluster/matrix/17.mtx
semcluster/matrix/18.mtx
semcluster/matrix/19.mtx
semcluster/matrix/2.mtx
semcluster/matrix/20.mtx
semcluster/matrix/21.mtx
semcluster/matrix/22.mtx
semcluster/matrix/23.mtx
semcluster/matrix/24.mtx
semcluster/matrix/25.mtx
semcluster/matrix/26.mtx
semcluster/matrix/27.mtx
semcluster/matrix/28.mtx
semcluster/matrix/29.mtx
semcluster/matrix/3.mtx
semcluster/matrix/30.mtx
semcluster/matrix/31.mtx
semcluster/matrix/32.mtx
semcluster/matrix/33.mtx
semcluster/matrix/34.mtx
semcluster/matrix/35.mtx
semcluster/matrix/36.mtx
semcluster/matrix/37.mtx
semcluster/matrix/38.mtx
semcluster/matrix/39.mtx
semcluster/matrix/4.mtx
semcluster/matrix/40.mtx
semcluster/matrix/41.mtx
semcluster/matrix/42.mtx
semcluster/matrix/43.mtx
semcluster/matrix/44.mtx
semcluster/matrix/45.mtx
semcluster/matrix/46.mtx
semcluster/matrix/47.mtx
semcluster/matrix/48.mtx
semcluster/matrix/49.mtx
semcluster/matrix/5.mtx
semcluster/matrix/50.mtx
semcluster/matrix/51.mtx
semcluster/matrix/52.mtx
semcluster/matrix/53.mtx
semcluster/matrix/54.mtx
semcluster/matrix/55.mtx
semcluster/matrix/56.mtx
semcluster/matrix/57.mtx
semcluster/matrix/58.mtx
semcluster/matrix/59.mtx
semcluster/matrix/6.mtx
semcluster/matrix/60.mtx
semcluster/matrix/61.mtx
semcluster/matrix/62.mtx
semcluster/matrix/63.mtx
semcluster/matrix/64.mtx
semcluster/matrix/65.mtx
semcluster-0.0.1.dist-info/METADATA
semcluster-0.0.1.dist-info/WHEEL
semcluster-0.0.1.dist-info/top_level.txt
semcluster-0.0.1.dist-info/RECORD
