Metadata-Version: 2.1
Name: semcluster
Version: 0.0.1
Summary: Unsupervised automatic keyphrase extraction
Home-page: UNKNOWN
Author: Palle Klewitz
License: UNKNOWN
Platform: UNKNOWN
Classifier: Programming Language :: Python :: 3
Classifier: Operating System :: OS Independent
